{
    "LoginPacket": {
        "id": 130,
        "fields": {
            "username": "String",
            "protocol1": "IntBE",
            "protocol2": "IntBE"
        }
    },
    "LoginStatusPacket": {
        "id": 131,
        "fields": {
            "status": "IntBE"
        }
    },
    "ReadyPacket": {
        "id": 132,
        "fields": {
            "status": "UnsignedByte"
        }
    },
    "MessagePacket": {
        "id": 133,
        "fields": {
            "message": "String"
        }
    },
    "SetTimePacket": {
        "id": 134,
        "fields": {
            "time": "IntBE"
        }
    },
    "StartGamePacket": {
        "id": 135,
        "fields": {
            "seed": "IntBE",
            "generator": "IntBE",
            "gamemode": "IntBE",
            "entityId": "IntBE",
            "x": "FloatBE",
            "y": "FloatBE",
            "z": "FloatBE"
        }
    },
    "AddMobPacket": {
        "id": 136,
        "fields": {
            "entityId": "IntBE",
            "type": "IntBE",
            "x": "FloatBE",
            "y": "FloatBE",
            "z": "FloatBE",
            "pitch": "Byte",
            "yaw": "Byte",
            "metadata": "Metadata"
        }
    },
    "AddPlayerPacket": {
        "id": 137,
        "fields": {
            "clientId": "UnsignedLongBE",
            "username": "String",
            "entityId": "IntBE",
            "x": "FloatBE",
            "y": "FloatBE",
            "z": "FloatBE",
            "pitch": "Byte",
            "yaw": "Byte",
            "item": "ShortBE",
            "meta": "ShortBE",
            "metadata": "Metadata"
        }
    },
    "RemovePlayerPacket": {
        "id": 138,
        "fields": {
            "entityId": "IntBE",
            "clientId": "UnsignedLongBE"
        }
    },
    "AddEntityPacket": {
        "id": 140,
        "fields": {
            "entityId": "IntBE",
            "type": "UnsignedByte",
            "x": "FloatBE",
            "y": "FloatBE",
            "z": "FloatBE",
            "hasMotion": "IntBE",
            "speedX": "ShortBE",
            "speedY": "ShortBE",
            "speedZ": "ShortBE"
        }
    },
    "RemoveEntityPacket": {
        "id": 141,
        "fields": {
            "entityId": "IntBE"
        }
    },
    "AddItemEntityPacket": {
        "id": 142,
        "fields": {
            "entityId": "IntBE",
            "item": "Item",
            "x": "FloatBE",
            "y": "FloatBE",
            "z": "FloatBE",
            "pitch": "Byte",
            "yaw": "Byte",
            "roll": "Byte"
        }
    },
    "TakeItemEntityPacket": {
        "id": 143,
        "fields": {
            "target": "IntBE",
            "entityId": "IntBE"
        }
    },
    "MoveEntityPacket": {
        "id": 144,
        "fields": {
            "entityId": "IntBE",
            "x": "FloatBE",
            "y": "FloatBE",
            "z": "FloatBE"
        }
    },
    "MoveEntityPacket_PosRot": {
        "id": 147,
        "fields": {
            "entityId": "IntBE",
            "x": "FloatBE",
            "y": "FloatBE",
            "z": "FloatBE",
            "pitch": "FloatBE",
            "yaw": "FloatBE"
        }
    },
    "MovePlayerPacket": {
        "id": 148,
        "fields": {
            "entityId": "IntBE",
            "x": "FloatBE",
            "y": "FloatBE",
            "z": "FloatBE",
            "pitch": "FloatBE",
            "yaw": "FloatBE"
        }
    },
    "PlaceBlockPacket": {
        "id": 149,
        "fields": {
            "entityId": "IntBE",
            "x": "IntBE",
            "z": "IntBE",
            "y": "UnsignedByte",
            "block": "UnsignedByte",
            "meta": "UnsignedByte",
            "face": "UnsignedByte"
        }
    },
    "RemoveBlockPacket": {
        "id": 150,
        "fields": {
            "entityId": "IntBE",
            "x": "IntBE",
            "z": "IntBE",
            "y": "UnsignedByte"
        }
    },
    "UpdateBlockPacket": {
        "id": 151,
        "fields": {
            "x": "IntBE",
            "z": "IntBE",
            "y": "UnsignedByte",
            "block": "UnsignedByte",
            "meta": "UnsignedByte"
        }
    },
    "AddPaintingPacket": {
        "id": 152,
        "fields": {
            "entityId": "IntBE",
            "x": "IntBE",
            "y": "IntBE",
            "z": "IntBE",
            "direction": "IntBE",
            "title": "String"
        }
    },
    "ExplodePacket": {
        "id": 153,
        "fields": {
            "x": "FloatBE",
            "y": "FloatBE",
            "z": "FloatBE",
            "radious": "FloatBE",
            "records": "Records"
        }
    },
    "LevelEventPacket": {
        "id": 154,
        "fields": {
            "eventId": "ShortBE",
            "x": "ShortBE",
            "y": "ShortBE",
            "z": "ShortBE",
            "data": "IntBE"
        }
    },
    "TileEventPacket": {
        "id": 155,
        "fields": {
            "x": "IntBE",
            "y": "IntBE",
            "z": "IntBE",
            "case1": "IntBE",
            "case2": "IntBE"
        }
    },
    "EntityEventPacket": {
        "id": 156,
        "fields": {
            "entityId": "IntBE",
            "event": "UnsignedByte"
        }
    },
    "RequestChunkPacket": {
        "id": 157,
        "fields": {
            "x": "IntBE",
            "z": "IntBE"
        }
    },
    "ChunkDataPacket": {
        "id": 158,
        "fields": {
            "x": "IntBE",
            "z": "IntBE",
            "data": "ChunkData"
        }
    },
    "PlayerEquipmentPacket": {
        "id": 159,
        "fields": {
            "entityId": "IntBE",
            "block": "UnsignedShortBE",
            "meta": "UnsignedShortBE"
        }
    },
    "PlayerArmorEquipmentPacket": {
        "id": 160,
        "fields": {
            "entityId": "IntBE",
            "slot0": "UnsignedByte",
            "slot1": "UnsignedByte",
            "slot2": "UnsignedByte",
            "slot3": "UnsignedByte"
        }
    },
    "InteractPacket": {
        "id": 161,
        "fields": {
            "action": "UnsignedByte",
            "entityId": "IntBE",
            "target": "IntBE"
        }
    },
    "UseItemPacket": {
        "id": 162,
        "fields": {
            "x": "IntBE",
            "y": "IntBE",
            "z": "IntBE",
            "face": "IntBE",
            "block": "UnsignedShortBE",
            "meta": "UnsignedByte",
            "entityId": "IntBE",
            "fx": "FloatBE",
            "fy": "FloatBE",
            "fz": "FloatBE"
        }
    },
    "PlayerActionPacket": {
        "id": 163,
        "fields": {
            "action": "IntBE",
            "x": "IntBE",
            "y": "IntBE",
            "z": "IntBE",
            "face": "IntBE",
            "entityId": "IntBE"
        }
    },
    "HurtArmorPacket": {
        "id": 165,
        "fields": {
            "health": "Byte"
        }
    },
    "SetEntityDataPacket": {
        "id": 166,
        "fields": {
            "entityId": "IntBE",
            "metadata": "Metadata"
        }
    },
    "SetEntityMotionPacket": {
        "id": 167,
        "fields": {
            "entityId": "IntBE",
            "speedX": "ShortBE",
            "speedY": "ShortBE",
            "speedZ": "ShortBE"
        }
    },
    "SetHealthPacket": {
        "id": 168,
        "fields": {
            "health": "UnsignedByte"
        }
    },
    "SetSpawnPositionPacket": {
        "id": 169,
        "fields": {
            "x": "IntBE",
            "z": "IntBE",
            "y": "UnsignedByte"
        }
    },
    "AnimatePacket": {
        "id": 170,
        "fields": {
            "action": "UnsignedByte",
            "entityId": "IntBE"
        }
    },
    "RespawnPacket": {
        "id": 171,
        "fields": {
            "entityId": "IntBE",
            "x": "FloatBE",
            "y": "FloatBE",
            "z": "FloatBE"
        }
    },
    "SendInventoryPacket": {
        "id": 172,
        "fields": {
            "entityId": "IntBE",
            "windowId": "UnsignedByte",
            "slots": "Items",
            "armor": "Armor"
        }
    },
    "DropItemPacket": {
        "id": 173,
        "fields": {
            "entityId": "IntBE",
            "type": "UnsignedByte",
            "item": "Item"
        }
    },
    "ContainerOpenPacket": {
        "id": 174,
        "fields": {
            "windowId": "UnsignedByte",
            "type": "UnsignedByte",
            "slot": "UnsignedByte",
            "title": "String"
        }
    },
    "ContainerClosePacket": {
        "id": 175,
        "fields": {
            "windowId": "UnsignedByte"
        }
    },
    "ContainerSetSlotPacket": {
        "id": 176,
        "fields": {
            "windowId": "UnsignedByte",
            "slot": "UnsignedShortBE",
            "item": "Item"
        }
    },
    "ContainerSetDataPacket": {
        "id": 177,
        "fields": {
            "windowId": "UnsignedByte",
            "property": "ShortBE",
            "value": "ShortBE"
        }
    },
    "ContainerSetContentPacket": {
        "id": 178,
        "fields": {
            "windowId": "UnsignedByte",
            "slots": "Items"
        }
    },
    "ContainerAckPacket": {
        "id": 179,
        "fields": {
            "windowId": "UnsignedByte",
            "unknown1": "ShortBE"
        }
    },
    "ChatPacket": {
        "id": 180,
        "fields": {
            "message": "String"
        }
    },
    "SignUpdatePacket": {
        "id": 181,
        "fields": {
            "x": "ShortBE",
            "y": "UnsignedByte",
            "z": "ShortBE",
            "lines": "String"
        }
    },
    "AdventureSettingsPacket": {
        "id": 182,
        "fields": {
            "flags": "UnsignedIntBE"
        }
    }
}
